collective.volto.contactsblock-1.0.1-py3.11-nspkg.pth
collective/volto/contactsblock/__init__.py
collective/volto/contactsblock/configure.zcml
collective/volto/contactsblock/interfaces.py
collective/volto/contactsblock/permissions.zcml
collective/volto/contactsblock/setuphandlers.py
collective/volto/contactsblock/testing.py
collective/volto/contactsblock/browser/__init__.py
collective/volto/contactsblock/browser/configure.zcml
collective/volto/contactsblock/browser/controlpanel.py
collective/volto/contactsblock/browser/overrides/.gitkeep
collective/volto/contactsblock/browser/static/.gitkeep
collective/volto/contactsblock/locales/README.rst
collective/volto/contactsblock/locales/__init__.py
collective/volto/contactsblock/locales/collective.volto.contactsblock.pot
collective/volto/contactsblock/locales/update.py
collective/volto/contactsblock/locales/update.sh
collective/volto/contactsblock/locales/en/LC_MESSAGES/collective.volto.contactsblock.po
collective/volto/contactsblock/locales/it/LC_MESSAGES/collective.volto.contactsblock.po
collective/volto/contactsblock/profiles/default/browserlayer.xml
collective/volto/contactsblock/profiles/default/catalog.xml
collective/volto/contactsblock/profiles/default/controlpanel.xml
collective/volto/contactsblock/profiles/default/metadata.xml
collective/volto/contactsblock/profiles/default/registry.xml
collective/volto/contactsblock/profiles/default/rolemap.xml
collective/volto/contactsblock/profiles/uninstall/browserlayer.xml
collective/volto/contactsblock/restapi/__init__.py
collective/volto/contactsblock/restapi/configure.zcml
collective/volto/contactsblock/restapi/controlpanel.py
collective/volto/contactsblock/restapi/get.py
collective/volto/contactsblock/tests/__init__.py
collective/volto/contactsblock/tests/test_setup.py
collective_volto_contactsblock-1.0.1.dist-info/LICENSE.GPL
collective_volto_contactsblock-1.0.1.dist-info/LICENSE.rst
collective_volto_contactsblock-1.0.1.dist-info/METADATA
collective_volto_contactsblock-1.0.1.dist-info/WHEEL
collective_volto_contactsblock-1.0.1.dist-info/entry_points.txt
collective_volto_contactsblock-1.0.1.dist-info/namespace_packages.txt
collective_volto_contactsblock-1.0.1.dist-info/top_level.txt
collective_volto_contactsblock-1.0.1.dist-info/RECORD
