Metadata-Version: 2.2
Name: collective.volto.contactsblock
Version: 1.0.1
Summary: An add-on for Plone
Home-page: https://github.com/collective/collective.volto.contactsblock
Author: RedTurtle
Author-email: roman.kysil@redturtle.it
License: GPL version 2
Project-URL: PyPI, https://pypi.org/project/collective.volto.contactsblock/
Project-URL: Source, https://github.com/collective/collective.volto.contactsblock
Project-URL: Tracker, https://github.com/collective/collective.volto.contactsblock/issues
Keywords: Python Plone CMS
Classifier: Environment :: Web Environment
Classifier: Framework :: Plone
Classifier: Framework :: Plone :: Addon
Classifier: Framework :: Plone :: 5.2
Classifier: Framework :: Plone :: 6.0
Classifier: Programming Language :: Python
Classifier: Programming Language :: Python :: 3.9
Classifier: Programming Language :: Python :: 3.10
Classifier: Programming Language :: Python :: 3.11
Classifier: Operating System :: OS Independent
Classifier: License :: OSI Approved :: GNU General Public License v2 (GPLv2)
Requires-Python: >=3.7
License-File: LICENSE.GPL
License-File: LICENSE.rst
Requires-Dist: setuptools
Requires-Dist: z3c.jbot
Requires-Dist: plone.api>=1.8.4
Requires-Dist: plone.app.dexterity
Provides-Extra: test
Requires-Dist: plone.app.testing; extra == "test"
Requires-Dist: plone.testing>=5.0.0; extra == "test"
Requires-Dist: plone.app.contenttypes; extra == "test"
Dynamic: author
Dynamic: author-email
Dynamic: classifier
Dynamic: description
Dynamic: home-page
Dynamic: keywords
Dynamic: license
Dynamic: project-url
Dynamic: provides-extra
Dynamic: requires-dist
Dynamic: requires-python
Dynamic: summary
